feincms_photos-0.3.0.dist-info/DESCRIPTION.rst
feincms_photos-0.3.0.dist-info/METADATA
feincms_photos-0.3.0.dist-info/metadata.json
feincms_photos-0.3.0.dist-info/RECORD
feincms_photos-0.3.0.dist-info/top_level.txt
feincms_photos-0.3.0.dist-info/WHEEL
photos/__init__.py
photos/admin.py
photos/models.py
photos/views.py
photos/migrations/0001_initial.py
photos/migrations/__init__.py
photos/south_migrations/0001_initial.py
photos/south_migrations/__init__.py
photos/templates/photos/album_detail.html
photos/templates/photos/album_list.html
